xia_engine_redis/__init__.py
xia_engine_redis/engine.cpython-311-darwin.so
xia_engine_redis-0.0.2.dist-info/LICENSE.txt
xia_engine_redis-0.0.2.dist-info/METADATA
xia_engine_redis-0.0.2.dist-info/WHEEL
xia_engine_redis-0.0.2.dist-info/top_level.txt
xia_engine_redis-0.0.2.dist-info/RECORD
