Metadata-Version: 2.1
Name: xia-engine-redis
Version: 0.0.2
Home-page: https://develop.x-i-a.com/docs/xia-engine-redis/0.0.2/index.html
Author: X-I-A
Author-email: admin@x-i-a.com
Requires-Python: >=3.9
License-File: LICENSE.txt
Requires-Dist: redis
Requires-Dist: xia-fields
Requires-Dist: xia-engine
